wagtail_purge/__init__.py
wagtail_purge/admin_urls.py
wagtail_purge/apps.py
wagtail_purge/views.py
wagtail_purge/wagtail_hooks.py
wagtail_purge/templates/index.html
wagtail_purge-0.4.0.dist-info/LICENSE
wagtail_purge-0.4.0.dist-info/METADATA
wagtail_purge-0.4.0.dist-info/WHEEL
wagtail_purge-0.4.0.dist-info/top_level.txt
wagtail_purge-0.4.0.dist-info/RECORD
